{"name":"./source.rinha","expression":{"kind":"Let","name":{"text":"a","location":{"start":4,"end":5,"filename":"./source.rinha"}},"value":{"kind":"Int","value":1,"location":{"start":8,"end":9,"filename":"./source.rinha"}},"next":{"kind":"Let","name":{"text":"b","location":{"start":15,"end":16,"filename":"./source.rinha"}},"value":{"kind":"Str","value":"Text","location":{"start":19,"end":25,"filename":"./source.rinha"}},"next":{"kind":"Let","name":{"text":"c","location":{"start":31,"end":32,"filename":"./source.rinha"}},"value":{"kind":"Tuple","first":{"kind":"Var","text":"x","location":{"start":36,"end":37,"filename":"./source.rinha"}},"second":{"kind":"Var","text":"y","location":{"start":39,"end":40,"filename":"./source.rinha"}},"location":{"start":35,"end":41,"filename":"./source.rinha"}},"next":{"kind":"Let","name":{"text":"d","location":{"start":47,"end":48,"filename":"./source.rinha"}},"value":{"kind":"Tuple","first":{"kind":"Var","text":"c","location":{"start":52,"end":53,"filename":"./source.rinha"}},"second":{"kind":"Int","value":2,"location":{"start":55,"end":56,"filename":"./source.rinha"}},"location":{"start":51,"end":57,"filename":"./source.rinha"}},"next":{"kind":"Let","name":{"text":"e","location":{"start":63,"end":64,"filename":"./source.rinha"}},"value":{"kind":"Function","parameters":[{"text":"f","location":{"start":71,"end":72,"filename":"./source.rinha"}}],"value":{"kind":"If","condition":{"kind":"Binary","lhs":{"kind":"First","value":{"kind":"Var","text":"f","location":{"start":92,"end":93,"filename":"./source.rinha"}},"location":{"start":86,"end":94,"filename":"./source.rinha"}},"op":"Eq","rhs":{"kind":"Int","value":1,"location":{"start":98,"end":99,"filename":"./source.rinha"}},"location":{"start":86,"end":99,"filename":"./source.rinha"}},"then":{"kind":"Tuple","first":{"kind":"Int","value":2,"location":{"start":111,"end":112,"filename":"./source.rinha"}},"second":{"kind":"Bool","value":false,"location":{"start":114,"end":119,"filename":"./source.rinha"}},"location":{"start":110,"end":120,"filename":"./source.rinha"}},"otherwise":{"kind":"Call","callee":{"kind":"Var","text":"e","location":{"start":145,"end":146,"filename":"./source.rinha"}},"arguments":[{"kind":"Tuple","first":{"kind":"First","value":{"kind":"Tuple","first":{"kind":"Int","value":1,"location":{"start":155,"end":156,"filename":"./source.rinha"}},"second":{"kind":"Int","value":2,"location":{"start":157,"end":158,"filename":"./source.rinha"}},"location":{"start":154,"end":159,"filename":"./source.rinha"}},"location":{"start":148,"end":160,"filename":"./source.rinha"}},"second":{"kind":"Int","value":2,"location":{"start":162,"end":163,"filename":"./source.rinha"}},"location":{"start":147,"end":164,"filename":"./source.rinha"}}],"location":{"start":145,"end":165,"filename":"./source.rinha"}},"location":{"start":83,"end":171,"filename":"./source.rinha"}},"location":{"start":67,"end":173,"filename":"./source.rinha"}},"next":{"kind":"Let","name":{"text":"g","location":{"start":179,"end":180,"filename":"./source.rinha"}},"value":{"kind":"Int","value":5,"location":{"start":183,"end":184,"filename":"./source.rinha"}},"next":{"kind":"Let","name":{"text":"g","location":{"start":190,"end":191,"filename":"./source.rinha"}},"value":{"kind":"Var","text":"b","location":{"start":194,"end":195,"filename":"./source.rinha"}},"next":{"kind":"Print","value":{"kind":"Var","text":"d","location":{"start":203,"end":204,"filename":"./source.rinha"}},"location":{"start":197,"end":205,"filename":"./source.rinha"}},"location":{"start":186,"end":205,"filename":"./source.rinha"}},"location":{"start":175,"end":205,"filename":"./source.rinha"}},"location":{"start":59,"end":205,"filename":"./source.rinha"}},"location":{"start":43,"end":205,"filename":"./source.rinha"}},"location":{"start":27,"end":205,"filename":"./source.rinha"}},"location":{"start":11,"end":205,"filename":"./source.rinha"}},"location":{"start":0,"end":205,"filename":"./source.rinha"}},"location":{"start":0,"end":205,"filename":"./source.rinha"}}
